LICENSE
wodoo_datalib/__init__.py
wodoo_datalib/csv_tools.py
wodoo_datalib/dataset.py
wodoo_datalib/env_vars.py
wodoo_datalib-0.0.2.dist-info/LICENSE
wodoo_datalib-0.0.2.dist-info/WHEEL
wodoo_datalib-0.0.2.dist-info/METADATA
wodoo_datalib-0.0.2.dist-info/RECORD
