Metadata-Version: 2.1
Name: wodoo-datalib
Version: 0.0.2
Summary: Dataabstractionlayer For Pandas
Home-page: https://gitlab.com/jksoftware1/wodoo-datalib
License: GPL-3
Keywords: pandas
Author: Joshua Kreuder
Author-email: joshua_kreuder@outlook.com
Requires-Python: >=3.8,<3.11
Classifier: License :: Other/Proprietary License
Classifier: Programming Language :: Python :: 3
Classifier: Programming Language :: Python :: 3.8
Classifier: Programming Language :: Python :: 3.9
Classifier: Programming Language :: Python :: 3.10
Requires-Dist: pandas (>=1.0.0,<1.4.0)
Project-URL: Repository, https://gitlab.com/jksoftware1/wodoo-datalib
